README.txt
setup.py
yars
yars.py
YARS.egg-info/PKG-INFO
YARS.egg-info/SOURCES.txt
YARS.egg-info/dependency_links.txt
YARS.egg-info/requires.txt
YARS.egg-info/top_level.txt