Metadata-Version: 1.0
Name: YARS
Version: 1.0
Summary: Yet Another RSS downloader
Home-page: http://mark.ossdl.de/tags/yars
Author: W-Mark Kubacki
Author-email: wmark+yars@hurrikane.de
License: http://www.opensource.org/licenses/rpl.php
Download-URL: http://mark.ossdl.de/tags/yars
Keywords: RSS,feeds,atom,cdf
Platform: POSIX
Platform: Windows
Classifier: Development Status :: 4 - Beta
Classifier: Intended Audience :: Developers
Classifier: Intended Audience :: End Users/Desktop
Classifier: Intended Audience :: System Administrators
Classifier: License :: Free for non-commercial use
Classifier: License :: Other/Proprietary License
Classifier: Natural Language :: English
Classifier: Operating System :: OS Independent
Classifier: Programming Language :: Python
Classifier: Topic :: Communications
Classifier: Topic :: Internet :: WWW/HTTP
Classifier: Topic :: Other/Nonlisted Topic
Classifier: Topic :: Communications :: File Sharing
Classifier: Topic :: Software Development :: Libraries :: Python Modules
